recoverymodel
