Metadata-Version: 2.1
Name: covid19-supplier-recovery
Version: 0.0.2
Summary: Modeling the recovery from covid19 crisis for suppliers to industries that have been severely impacted.
Home-page: https://gitlab.com/DareData-open-source/covid-19-supplier-recovery
Author: Ivo Bernardo, Sam Hopkins, Nuno Bras (DareData Engineering)
Author-email: ivo@daredata.engineering
License: UNKNOWN
Platform: UNKNOWN
